stocksmith/__init__.py
stocksmith/hello_world.py
stocksmith-0.1.0.1.dist-info/WHEEL
stocksmith-0.1.0.1.dist-info/METADATA
stocksmith-0.1.0.1.dist-info/RECORD
